Metadata-Version: 1.1
Name: dj-static-jl
Version: 0.0.7
Summary: Serve production static files with Django.
Home-page: https://github.com/jlachowski/dj-static
Author: Jaroslaw Lachowski
Author-email: jalachowski@gmail.com
License: BSD
Platform: any
Classifier: Environment :: Web Environment
Classifier: Intended Audience :: Developers
Classifier: License :: OSI Approved :: BSD License
Classifier: Operating System :: OS Independent
Classifier: Programming Language :: Python
Classifier: Programming Language :: Python :: 3
Classifier: Topic :: Internet :: WWW/HTTP :: Dynamic Content
Classifier: Topic :: Software Development :: Libraries :: Python Modules
